joblib_zstd/__init__.py
joblib_zstd/file.py
joblib_zstd/wrapper.py
joblib_zstd-0.1.1.dist-info/WHEEL
joblib_zstd-0.1.1.dist-info/METADATA
joblib_zstd-0.1.1.dist-info/RECORD
