Metadata-Version: 2.1
Name: joblib-zstd
Version: 0.1.1
Summary: Add Zstandard compression/decompression functionality for joblib
Home-page: https://github.com/roy-ht/joblib-zstd
License: MIT
Keywords: joblib,Zstandard
Author: Hiroyuki Tanaka
Author-email: aflc0x@gmail.com
Requires-Python: >=3.5,<4.0
Classifier: License :: OSI Approved :: MIT License
Classifier: Programming Language :: Python :: 3
Classifier: Programming Language :: Python :: 3.5
Classifier: Programming Language :: Python :: 3.6
Classifier: Programming Language :: Python :: 3.7
Classifier: Programming Language :: Python :: 3.8
Requires-Dist: joblib
Requires-Dist: zstandard
Project-URL: Repository, https://github.com/roy-ht/joblib-zstd
